examples/document_information_extraction_examples/utils.py
sap_business_document_processing/__init__.py
sap_business_document_processing/common/constants.py
sap_business_document_processing/common/exceptions.py
sap_business_document_processing/common/helpers.py
sap_business_document_processing/common/http_client_base.py
sap_business_document_processing/document_classification_client/__init__.py
sap_business_document_processing/document_classification_client/constants.py
sap_business_document_processing/document_classification_client/dc_api_client.py
sap_business_document_processing/document_information_extraction_client/__init__.py
sap_business_document_processing/document_information_extraction_client/constants.py
sap_business_document_processing/document_information_extraction_client/dox_api_client.py
sap_business_document_processing/document_information_extraction_client/endpoints.py
sap_business_document_processing/document_information_extraction_client/helpers.py
sap_business_document_processing-0.4.1.dist-info/LICENSE
sap_business_document_processing-0.4.1.dist-info/METADATA
sap_business_document_processing-0.4.1.dist-info/WHEEL
sap_business_document_processing-0.4.1.dist-info/top_level.txt
sap_business_document_processing-0.4.1.dist-info/RECORD
