Metadata-Version: 2.1
Name: sap-business-document-processing
Version: 0.4.1
Summary: Python client library for convenient usage of SAP Business Document Processing services
Home-page: https://github.com/sap/business-document-processing
Download-URL: https://pypi.org/project/sap-business-document-processing
Author: Alexander Bolshakov
Author-email: alexander.bolshakov@sap.com
License: apache-2.0
Keywords: SAP,business,document,processing,classification,information,extraction,machine learning
Classifier: Development Status :: 3 - Alpha
Classifier: Intended Audience :: Developers
Classifier: License :: OSI Approved :: Apache Software License
Classifier: Programming Language :: Python :: 3
License-File: LICENSE
Requires-Dist: urllib3 ~=1.26
Requires-Dist: requests ~=2.31
Requires-Dist: requests-oauthlib ~=1.3
